dlogging/__init__.py
dlogging/config.py
dlogging/factory.py
dlogging/utils.py
dlogging-0.5.dist-info/LICENSE.txt
dlogging-0.5.dist-info/METADATA
dlogging-0.5.dist-info/WHEEL
dlogging-0.5.dist-info/top_level.txt
dlogging-0.5.dist-info/RECORD
