Metadata-Version: 2.1
Name: dlogging
Version: 0.5
Summary: Dynamic logging
Home-page: https://github.com/drachenrio/dlogging
Author: Axariosu
Author-email: axariosu@gmail.com
License: MIT
Download-URL: https://github.com/drachenrio/dlogging
Platform: UNKNOWN
Classifier: Development Status :: 4 - Beta
Classifier: Intended Audience :: Developers
Classifier: License :: OSI Approved :: MIT License
Classifier: Natural Language :: English
Classifier: Operating System :: OS Independent
Classifier: Programming Language :: Python :: 3
Classifier: Programming Language :: Python :: 3.6
Classifier: Programming Language :: Python :: 3.7
Classifier: Topic :: Software Development :: Libraries :: Python Modules
Requires-Python: >=3.6
Provides-Extra: dev
Requires-Dist: pytest (>=5.0) ; extra == 'dev'
